svix/__init__.py
svix/exceptions.py
svix/py.typed
svix/webhooks.py
svix/api/__init__.py
svix/api/application.py
svix/api/authentication.py
svix/api/background_task.py
svix/api/client.py
svix/api/common.py
svix/api/connector.py
svix/api/endpoint.py
svix/api/environment.py
svix/api/event_type.py
svix/api/ingest.py
svix/api/ingest_endpoint.py
svix/api/ingest_source.py
svix/api/integration.py
svix/api/message.py
svix/api/message_attempt.py
svix/api/message_poller.py
svix/api/operational_webhook.py
svix/api/operational_webhook_endpoint.py
svix/api/statistics.py
svix/api/streaming.py
svix/api/streaming_event_type.py
svix/api/streaming_events.py
svix/api/streaming_sink.py
svix/api/streaming_stream.py
svix/api/svix.py
svix/api/errors/__init__.py
svix/api/errors/http_error.py
svix/api/errors/http_validation_error.py
svix/api/errors/validation_error.py
svix/models/__init__.py
svix/models/adobe_sign_config.py
svix/models/adobe_sign_config_out.py
svix/models/aggregate_event_types_out.py
svix/models/airwallex_config.py
svix/models/airwallex_config_out.py
svix/models/amazon_s3_patch_config.py
svix/models/api_token_out.py
svix/models/app_portal_access_in.py
svix/models/app_portal_access_out.py
svix/models/app_portal_capability.py
svix/models/app_usage_stats_in.py
svix/models/app_usage_stats_out.py
svix/models/application_in.py
svix/models/application_out.py
svix/models/application_patch.py
svix/models/application_token_expire_in.py
svix/models/azure_blob_storage_config.py
svix/models/azure_blob_storage_patch_config.py
svix/models/background_task_data.py
svix/models/background_task_finished_event.py
svix/models/background_task_finished_event2.py
svix/models/background_task_out.py
svix/models/background_task_status.py
svix/models/background_task_type.py
svix/models/checkbook_config.py
svix/models/checkbook_config_out.py
svix/models/common.py
svix/models/connector_in.py
svix/models/connector_kind.py
svix/models/connector_out.py
svix/models/connector_patch.py
svix-1.84.1.dist-info/METADATA
svix-1.84.1.dist-info/WHEEL
svix-1.84.1.dist-info/top_level.txt
svix-1.84.1.dist-info/RECORD
