Metadata-Version: 2.4
Name: svix
Version: 1.84.1
Summary: Svix webhooks API client and webhook verification library
Home-page: https://www.svix.com
Author: Svix
Author-email: development@svix.com
License: MIT
Keywords: svix,diahook,webhooks
Classifier: Intended Audience :: Developers
Classifier: Intended Audience :: Information Technology
Classifier: Operating System :: OS Independent
Classifier: Programming Language :: Python :: 3
Classifier: Programming Language :: Python
Classifier: Topic :: Software Development :: Libraries :: Application Frameworks
Classifier: Topic :: Software Development :: Libraries :: Python Modules
Classifier: Topic :: Software Development :: Libraries
Classifier: Topic :: Software Development
Classifier: Typing :: Typed
Classifier: License :: OSI Approved :: MIT License
Classifier: Programming Language :: Python :: 3 :: Only
Classifier: Programming Language :: Python :: 3.6
Classifier: Programming Language :: Python :: 3.7
Classifier: Programming Language :: Python :: 3.8
Requires-Python: >=3.6
Requires-Dist: pydantic>=2.10
Requires-Dist: httpx>=0.23.0
Requires-Dist: attrs>=21.3.0
Requires-Dist: standardwebhooks
Requires-Dist: python-dateutil
Requires-Dist: Deprecated
Requires-Dist: types-python-dateutil
Requires-Dist: types-Deprecated
Dynamic: author
Dynamic: author-email
Dynamic: classifier
Dynamic: description
Dynamic: description-content-type
Dynamic: home-page
Dynamic: keywords
Dynamic: license
Dynamic: requires-dist
Dynamic: requires-python
Dynamic: summary
